mirai/__init__.py
mirai/api.py
mirai/application.py
mirai/event.py
mirai/httpapi.py
mirai/sender.py
mirai/session.py
mirai/message/__init__.py
mirai/message/chain.py
mirai/message/element.py
mirai/message/messages.py
mirai_py-0.1a1.dev1.dist-info/LICENSE
mirai_py-0.1a1.dev1.dist-info/METADATA
mirai_py-0.1a1.dev1.dist-info/WHEEL
mirai_py-0.1a1.dev1.dist-info/top_level.txt
mirai_py-0.1a1.dev1.dist-info/RECORD
