Metadata-Version: 2.1
Name: mirai-py
Version: 0.1a1.dev1
Summary: Mirai python API
Home-page: https://github.com/lemon-chat/mirai-py
Author: Jun Wang
Author-email: jstzwj@aliyun.com
License: UNKNOWN
Project-URL: Bug Tracker, https://github.com/lemon-chat/mirai-py/issues
Platform: UNKNOWN
Classifier: Programming Language :: Python :: 3
Classifier: License :: OSI Approved :: MIT License
Classifier: Operating System :: OS Independent
Requires-Python: >=3.7
